{
  "attacks_available": 30,
  "attacks_per_member": 2,
  "attacks_used": 15,
  "data_status": "available",
  "end_time": "2026-07-20",
  "members": [
    {
      "attacks_available": 2,
      "attacks_used": 0,
      "average_stars": null,
      "nickname": "ayrym",
      "stars_earned": 0,
      "town_hall_level": 6
    },
    {
      "attacks_available": 2,
      "attacks_used": 2,
      "average_stars": 1.5,
      "nickname": "frogi",
      "stars_earned": 3,
      "town_hall_level": 6
    },
    {
      "attacks_available": 2,
      "attacks_used": 1,
      "average_stars": 3.0,
      "nickname": "Kedr",
      "stars_earned": 3,
      "town_hall_level": 7
    },
    {
      "attacks_available": 2,
      "attacks_used": 0,
      "average_stars": null,
      "nickname": "kent",
      "stars_earned": 0,
      "town_hall_level": 7
    },
    {
      "attacks_available": 2,
      "attacks_used": 0,
      "average_stars": null,
      "nickname": "Neron1x(fan)",
      "stars_earned": 0,
      "town_hall_level": 6
    },
    {
      "attacks_available": 2,
      "attacks_used": 1,
      "average_stars": 2.0,
      "nickname": "odlid",
      "stars_earned": 2,
      "town_hall_level": 7
    },
    {
      "attacks_available": 2,
      "attacks_used": 1,
      "average_stars": 3.0,
      "nickname": "oleg",
      "stars_earned": 3,
      "town_hall_level": 6
    },
    {
      "attacks_available": 2,
      "attacks_used": 2,
      "average_stars": 2.0,
      "nickname": "PANDA",
      "stars_earned": 4,
      "town_hall_level": 5
    },
    {
      "attacks_available": 2,
      "attacks_used": 2,
      "average_stars": 2.5,
      "nickname": "Ronnurik",
      "stars_earned": 5,
      "town_hall_level": 5
    },
    {
      "attacks_available": 2,
      "attacks_used": 2,
      "average_stars": 3.0,
      "nickname": "SvisBee",
      "stars_earned": 6,
      "town_hall_level": 7
    },
    {
      "attacks_available": 2,
      "attacks_used": 0,
      "average_stars": null,
      "nickname": "utena",
      "stars_earned": 0,
      "town_hall_level": 6
    },
    {
      "attacks_available": 2,
      "attacks_used": 1,
      "average_stars": 3.0,
      "nickname": "VB(;",
      "stars_earned": 3,
      "town_hall_level": 7
    },
    {
      "attacks_available": 2,
      "attacks_used": 2,
      "average_stars": 2.0,
      "nickname": "Али",
      "stars_earned": 4,
      "town_hall_level": 6
    },
    {
      "attacks_available": 2,
      "attacks_used": 0,
      "average_stars": null,
      "nickname": "залупий",
      "stars_earned": 0,
      "town_hall_level": 5
    },
    {
      "attacks_available": 2,
      "attacks_used": 1,
      "average_stars": 1.0,
      "nickname": "шкура",
      "stars_earned": 1,
      "town_hall_level": 5
    }
  ],
  "participants": 15,
  "stars_earned": 34,
  "state": "inWar"
}
